sftppathlib/__init__.py
sftppathlib-0.5.5.dist-info/licenses/LICENSE
sftppathlib-0.5.5.dist-info/METADATA
sftppathlib-0.5.5.dist-info/WHEEL
sftppathlib-0.5.5.dist-info/top_level.txt
sftppathlib-0.5.5.dist-info/RECORD
