Metadata-Version: 2.4
Name: sftppathlib
Version: 0.5.5
Summary: A Pathlib API for SFTP drive
Author: fourpoints
License-Expression: LGPL-2.1
Project-URL: Homepage, https://github.com/fourpoints/sftppathlib
Project-URL: Issues, https://github.com/fourpoints/sftppathlib/issues
Classifier: Programming Language :: Python :: 3
Classifier: Operating System :: OS Independent
Requires-Python: >=3.7
License-File: LICENSE
Requires-Dist: paramiko>=4.0.0
Requires-Dist: pathlib_abc==0.5
Dynamic: license-file
